airflow/providers/common/compat/LICENSE
airflow/providers/common/compat/__init__.py
airflow/providers/common/compat/get_provider_info.py
airflow/providers/common/compat/version_compat.py
airflow/providers/common/compat/assets/__init__.py
airflow/providers/common/compat/lineage/__init__.py
airflow/providers/common/compat/lineage/entities.py
airflow/providers/common/compat/lineage/hook.py
airflow/providers/common/compat/openlineage/__init__.py
airflow/providers/common/compat/openlineage/facet.py
airflow/providers/common/compat/openlineage/utils/__init__.py
airflow/providers/common/compat/openlineage/utils/spark.py
airflow/providers/common/compat/openlineage/utils/sql.py
airflow/providers/common/compat/openlineage/utils/utils.py
airflow/providers/common/compat/security/__init__.py
airflow/providers/common/compat/security/permissions.py
airflow/providers/common/compat/standard/__init__.py
airflow/providers/common/compat/standard/operators.py
airflow/providers/common/compat/standard/triggers.py
airflow/providers/common/compat/standard/utils.py
apache_airflow_providers_common_compat-1.4.0.dist-info/entry_points.txt
apache_airflow_providers_common_compat-1.4.0.dist-info/WHEEL
apache_airflow_providers_common_compat-1.4.0.dist-info/METADATA
apache_airflow_providers_common_compat-1.4.0.dist-info/RECORD
