Metadata-Version: 2.3
Name: apache-airflow-providers-common-compat
Version: 1.4.0
Summary: Provider package apache-airflow-providers-common-compat for Apache Airflow
Keywords: airflow-provider,common.compat,airflow,integration
Author-email: Apache Software Foundation <dev@airflow.apache.org>
Maintainer-email: Apache Software Foundation <dev@airflow.apache.org>
Requires-Python: ~=3.9
Classifier: Development Status :: 5 - Production/Stable
Classifier: Environment :: Console
Classifier: Environment :: Web Environment
Classifier: Intended Audience :: Developers
Classifier: Intended Audience :: System Administrators
Classifier: Framework :: Apache Airflow
Classifier: Framework :: Apache Airflow :: Provider
Classifier: License :: OSI Approved :: Apache Software License
Classifier: Programming Language :: Python :: 3.9
Classifier: Programming Language :: Python :: 3.10
Classifier: Programming Language :: Python :: 3.11
Classifier: Programming Language :: Python :: 3.12
Classifier: Topic :: System :: Monitoring
Requires-Dist: apache-airflow>=2.9.0
Requires-Dist: apache-airflow-providers-openlineage ; extra == "openlineage"
Requires-Dist: apache-airflow-providers-standard ; extra == "standard"
Project-URL: Bug Tracker, https://github.com/apache/airflow/issues
Project-URL: Changelog, https://airflow.apache.org/docs/apache-airflow-providers-common-compat/1.4.0/changelog.html
Project-URL: Documentation, https://airflow.apache.org/docs/apache-airflow-providers-common-compat/1.4.0
Project-URL: Slack Chat, https://s.apache.org/airflow-slack
Project-URL: Source Code, https://github.com/apache/airflow
Project-URL: Twitter, https://x.com/ApacheAirflow
Project-URL: YouTube, https://www.youtube.com/channel/UCSXwxpWZQ7XZ1WL3wqevChA/
Provides-Extra: openlineage
Provides-Extra: standard
